mercury/__init__.py
mercury/core/__init__.py
mercury/core/account.py
mercury/core/broker.py
mercury/core/engine.py
mercury/core/order.py
mercury/core/position.py
mercury/core/strategy.py
mercury/core/timeseries.py
mercury/extras/__init__.py
mercury/extras/brokers/__init__.py
mercury/extras/brokers/ig.py
mercury/extras/brokers/oanda.py
mercury/extras/brokers/xapi.py
mercury/extras/datasources/__init__.py
mercury/extras/datasources/alphavantage.py
mercury/extras/datasources/csv.py
mercury/extras/datasources/quandl.py
mercury/extras/strategies/__init__.py
mercury/extras/strategies/sma_crossover.py
mercury/lib/__init__.py
mercury/lib/baseclass.py
mercury/lib/client.py
mercury/lib/connectors.py
mercury/lib/datasource.py
mercury/lib/datastore.py
mercury/lib/exceptions.py
mercury/lib/flexarray.py
materya_mercury-1.0.0rc3.dist-info/LICENSE
materya_mercury-1.0.0rc3.dist-info/METADATA
materya_mercury-1.0.0rc3.dist-info/WHEEL
materya_mercury-1.0.0rc3.dist-info/top_level.txt
materya_mercury-1.0.0rc3.dist-info/RECORD
