Metadata-Version: 2.1
Name: materya-mercury
Version: 1.0.0rc3
Summary: Full suite for automated quantitative trading in Python
Home-page: https://github.com/materya/mercury
Author: Richard Kemp
Author-email: sylver@materya.io
Maintainer: Richard Kemp
Maintainer-email: sylver@materya.io
License: GNU General Public License version 3
Keywords: algorithmic,bot,forex,ml,quant,quantitative,stocks,trading
Platform: UNKNOWN
Classifier: Development Status :: 4 - Beta
Classifier: License :: OSI Approved :: GNU General Public License v3 (GPLv3)
Classifier: Operating System :: OS Independent
Classifier: Programming Language :: Python :: 3
Classifier: Programming Language :: Python :: 3.6
Classifier: Programming Language :: Python :: 3.7
Classifier: Programming Language :: Python :: 3.8
Classifier: Topic :: Office/Business :: Financial :: Investment
Classifier: Topic :: Scientific/Engineering :: Visualization
Classifier: Topic :: Software Development
Classifier: Topic :: Software Development :: Libraries
Classifier: Topic :: Software Development :: Libraries :: Python Modules
Classifier: Typing :: Typed
Requires-Dist: numpy (==1.20.1)
Requires-Dist: pandas (==1.2.2)
Requires-Dist: ta-lib (==0.4.19)
Requires-Dist: websockets
Provides-Extra: dev
Requires-Dist: flake8 ; extra == 'dev'
Requires-Dist: mypy ; extra == 'dev'
Requires-Dist: pandas-stubs ; extra == 'dev'
Requires-Dist: twine ; extra == 'dev'
Provides-Extra: doc
Requires-Dist: pdoc3 ; extra == 'doc'
Provides-Extra: extra_broker_ig
Requires-Dist: requests ; extra == 'extra_broker_ig'
Provides-Extra: extra_broker_oanda
Requires-Dist: oandapyV20 (==0.6.3) ; extra == 'extra_broker_oanda'
Provides-Extra: extra_datasource_alphavantage
Requires-Dist: alpha-vantage (==2.3.1) ; extra == 'extra_datasource_alphavantage'
Provides-Extra: extra_datasource_quandl
Requires-Dist: quandl (==3.6.1) ; extra == 'extra_datasource_quandl'
Provides-Extra: extras
Requires-Dist: alpha-vantage (==2.3.1) ; extra == 'extras'
Requires-Dist: quandl (==3.6.1) ; extra == 'extras'
Requires-Dist: requests ; extra == 'extras'
Requires-Dist: oandapyV20 (==0.6.3) ; extra == 'extras'
Provides-Extra: test
Requires-Dist: flake8-annotations-coverage ; extra == 'test'
Requires-Dist: flake8-bandit ; extra == 'test'
Requires-Dist: flake8-builtins ; extra == 'test'
Requires-Dist: flake8-commas ; extra == 'test'
Requires-Dist: flake8-docstrings ; extra == 'test'
Requires-Dist: flake8-import-order ; extra == 'test'
Requires-Dist: flake8-quotes ; extra == 'test'
Requires-Dist: pytest ; extra == 'test'
Requires-Dist: pytest-cov ; extra == 'test'
Requires-Dist: pytest-flake8 ; extra == 'test'
Requires-Dist: pep8-naming ; extra == 'test'
